radiation/__init__.py
radiation/config.py
radiation/context.py
radiation/filters/__init__.py
radiation/filters/line_limit.py
radiation/filters/patch.py
radiation/gen.py
radiation/mutation.py
radiation/mutators/__init__.py
radiation/mutators/binops.py
radiation/mutators/boolops.py
radiation/mutators/compare.py
radiation/mutators/constants.py
radiation/mutators/invert.py
radiation/mutators/unaryops.py
radiation/py.typed
radiation/radiation.py
radiation/runners/__init__.py
radiation/runners/tempdir.py
radiation/types.py
radiation-0.2.0.dist-info/entry_points.txt
radiation-0.2.0.dist-info/LICENSE
radiation-0.2.0.dist-info/WHEEL
radiation-0.2.0.dist-info/METADATA
radiation-0.2.0.dist-info/RECORD
