Metadata-Version: 2.1
Name: radiation
Version: 0.2.0
Summary: Extendable mutation testing framework
Home-page: https://github.com/radiation-mutations/radiation
License: MIT
Keywords: testing,mutation
Author: Yanay Goor
Author-email: yanay.goor@gmail.com
Requires-Python: >=3.8,<4.0
Classifier: License :: OSI Approved :: MIT License
Classifier: Programming Language :: Python :: 3
Classifier: Programming Language :: Python :: 3.10
Classifier: Programming Language :: Python :: 3.8
Classifier: Programming Language :: Python :: 3.9
Requires-Dist: click (>=8.1.2,<9.0.0)
Requires-Dist: setuptools (>=62.1.0,<63.0.0)
Requires-Dist: toml (>=0.10.2,<0.11.0)
Requires-Dist: whatthepatch (>=1.0.2,<2.0.0)
Project-URL: Documentation, https://github.com/radiation-mutations/radiation
Project-URL: Repository, https://github.com/radiation-mutations/radiation
